<?xml version="1.0" encoding="utf-8"?>
<openerp>
    <data>
        <record id="view_sie_subject_unit_form" model="ir.ui.view">
            <field name="name">sie.subject.unit.form</field>
            <field name="model">sie.subject.unit</field>
            <field name="arch" type="xml">
                <form string="Learning Unit">
                    <sheet>
                        <div class="oe_title">
                            <label for="number" class="oe_edit_only" string="Index"/>
                            <h1>
                                <field name="number" class="oe_inline" placeholder="1"/>
                            </h1>
                        </div>
                        <group col="4">
                            <field name="name" colspan="4"/>
                            <field name="description" colspan="4"/>
                            <field name="hours" attrs="{'invisible':[('last_child','=',False)]}"/>
                            <field name="total_hours" attrs="{'invisible':[('last_child','=',True)]}"/>
                            <field name="last_child" invisible="1"/>
                        </group>
                        <notebook>
                            <page string="Child Units">
                                <field name="child_ids" nolabel="1"/>
                            </page>
                        </notebook>
                    </sheet>
                </form>
            </field>
        </record>
        <record id="view_sie_subject_unit_tree" model="ir.ui.view">
            <field name="name">sie.subject.unit.tree</field>
            <field name="model">sie.subject.unit</field>
            <field name="arch" type="xml">
                <tree string="Learning Unit">
                    <field name="number"/>
                    <field name="name"/>
                    <field name="hours"/>
                </tree>
            </field>
        </record>
    </data>
</openerp>